smartproxy/smartproxy.py
pyproxywebscrapper-4.0.0.dist-info/LICENSE
pyproxywebscrapper-4.0.0.dist-info/METADATA
pyproxywebscrapper-4.0.0.dist-info/WHEEL
pyproxywebscrapper-4.0.0.dist-info/top_level.txt
pyproxywebscrapper-4.0.0.dist-info/RECORD
