Metadata-Version: 2.1
Name: pyproxywebscrapper
Version: 4.0.0
Summary: This Package will be useful for people who are doing webscrapping
Home-page: https://github.com/soumilshah1995/AppleStock
Author: Soumil Nitin Shah
Author-email: soushah@my.bridgeport.edu
License: MIT
Platform: UNKNOWN
Classifier: License :: OSI Approved :: MIT License
Classifier: Programming Language :: Python :: 3
Classifier: Programming Language :: Python :: 3.7
Requires-Dist: requests
